quakeanalysis
