Metadata-Version: 1.1
Name: quakeanalysis
Version: 0.0.7
Summary: analysing earthquake data
Home-page: UNKNOWN
Author: Christopher Collins
Author-email: mr.collins.llb@gmail.com
License: MIT
Keywords: calculator
Platform: UNKNOWN
Classifier: Development Status :: 5 - Production/Stable
Classifier: Intended Audience :: Education
Classifier: Operating System :: Microsoft :: Windows :: Windows 10
Classifier: License :: OSI Approved :: MIT License
Classifier: Programming Language :: Python :: 3
